{
    "Item":{
        "types": ["weapon", "gear", "skill", "special_stat"]
    },
    "templates": {
        "skill": {
                "skill_name": "New Skill",
                "base":0,
                "hardDice":0,
                "wiggleDice":0,
                "tempMod":0,
                "linkedStat": "None",
                "spec":false,
                "specName":""
            },
        "weapon": {
            "weapon_name": "Name",
            "weapon_desc": "Description",
            "weapon_type": "melee",
            "damage_shock_bonus":0,
            "damage_kill_bonus":0,
            "attack_skill": ""
        },
        "gear": {
            "gear_name":"New Gear Item",
            "gear_cost":"$100.00",
            "gear_d":0,
            "gear_wd":0,
            "gear_hd":0,
            "gear_desc":"This is a piece of gear."
        },
        "special_stat":
        {
                "spec_stat_name": "New Special Stat",
                "base":0,
                "hardDice":0,
                "wiggleDice":0,
                "tempMod":0
        }
    },
    "Actor":{
        "types": ["pc", "npc", "squad"],
        "templates":{
            "pc": {
                "templates": ["bio", "stats"]
            },
            "npc": {
                "templates": ["bio", "stats"]
            },
            "squad": {
                "templates": ["squadTemplate"]
            },
            "squadTemplate":{
                "dicePool": 5
            },
            "bio":{
                "char_bio_text": "--"
            },
            "stats": {
                    "body": {
                        "base":0,
                        "hardDice":0,
                        "wiggleDice":0,
                        "tempMod":0
                    },
                    "coordination":{
                        "base":0,
                        "hardDice":0,
                        "wiggleDice":0,
                        "tempMod":0
                    },
                    "sense": {
                        "base":0,
                        "hardDice":0,
                        "wiggleDice":0,
                        "tempMod":0
                    },
                    "mind": {
                        "base":0,
                        "hardDice":0,
                        "wiggleDice":0,
                        "tempMod":0
                    },
                    "command": {
                        "base":0,
                        "hardDice":0,
                        "wiggleDice":0,
                        "tempMod":0
                    }                
            }
        }
    }
}